MANIFEST.in
README.rst
setup.py
zhot/__init__.py
zhot/__main__.py
zhot/diagram.css
zhot/diagram.py
zhot/zhot.py
zhot.egg-info/PKG-INFO
zhot.egg-info/SOURCES.txt
zhot.egg-info/dependency_links.txt
zhot.egg-info/entry_points.txt
zhot.egg-info/requires.txt
zhot.egg-info/top_level.txt