Metadata-Version: 1.2
Name: zhot
Version: 0.2.1
Summary: Command-line implementation of Zhot, an extensible Scissors-Paper-Stone game.
Home-page: https://github.com/AmyDeeDempster/zhot
Author: Amy Dee DEMPSTER
Author-email: amy.dempster@student.rmit.edu.au
License: UNKNOWN
Platform: UNKNOWN
Requires-Python: >3.5
